logging_timehandler/__init__.py
logging_timehandler/timehandler.py
logging_timehandler-0.1.0.dist-info/METADATA
logging_timehandler-0.1.0.dist-info/WHEEL
logging_timehandler-0.1.0.dist-info/RECORD
